nba_headshot_downloader/__init__.py
nba_headshot_downloader/headshots.py
nba_headshot_downloader-1.0.0.dist-info/LICENSE
nba_headshot_downloader-1.0.0.dist-info/METADATA
nba_headshot_downloader-1.0.0.dist-info/WHEEL
nba_headshot_downloader-1.0.0.dist-info/top_level.txt
nba_headshot_downloader-1.0.0.dist-info/RECORD
