Metadata-Version: 2.2
Name: nba-headshot-downloader
Version: 1.0.0
Summary: A package to download headshots of nba players
Author-email: Troy Mireku <xapd421@gmail.com>
License: MIT License
Project-URL: Homepage, https://github.com/xapd421/nba-headshot-downloader
Project-URL: Issues, https://github.com/xapd421/nba-headshot-downloader/issues
Keywords: nba,headshot
Classifier: Programming Language :: Python :: 3
Classifier: Operating System :: OS Independent
Requires-Python: >=3.8
License-File: LICENSE
Requires-Dist: requests>=2.20.0
